{
  "characterId": 22,
  "rarity": 3,
  "attribute": "pure",
  "levelLimit": 40,
  "resourceSetName": "res022050",
  "sdResourceName": "sd022050",
  "episodes": {
    "entries": [
      {
        "episodeId": 2269,
        "episodeType": "standard",
        "situationId": 1391,
        "scenarioId": "episode1391",
        "appendPerformance": 200,
        "appendTechnique": 200,
        "appendVisual": 200,
        "releaseLevel": 1,
        "costs": {
          "entries": [
            {
              "resourceId": 4,
              "resourceType": "item",
              "quantity": 300,
              "lbBonus": 1
            },
            {
              "resourceId": 8,
              "resourceType": "item",
              "quantity": 100,
              "lbBonus": 1
            }
          ]
        },
        "rewards": {
          "entries": [
            {
              "resourceType": "star",
              "quantity": 25,
              "lbBonus": 1
            }
          ]
        },
        "title": [
          "お悩みシェアリング",
          "Sharing Troubles",
          "分享煩憂",
          "分享烦恼",
          "고민 공유"
        ],
        "characterId": 22
      },
      {
        "episodeId": 2270,
        "episodeType": "memorial",
        "situationId": 1391,
        "scenarioId": "memorial1391",
        "appendPerformance": 500,
        "appendTechnique": 500,
        "appendVisual": 500,
        "releaseLevel": 50,
        "costs": {
          "entries": [
            {
              "resourceId": 4,
              "resourceType": "item",
              "quantity": 1800,
              "lbBonus": 1
            },
            {
              "resourceId": 8,
              "resourceType": "item",
              "quantity": 1200,
              "lbBonus": 1
            },
            {
              "resourceId": 12,
              "resourceType": "item",
              "quantity": 300,
              "lbBonus": 1
            }
          ]
        },
        "rewards": {
          "entries": [
            {
              "resourceType": "star",
              "quantity": 50,
              "lbBonus": 1
            }
          ]
        },
        "title": [
          "あなたも私も、少しずつ",
          "Slowly Changing, You and I",
          "你我都，慢慢進步",
          "你和我，一点一点",
          "당신도 나도, 조금씩"
        ],
        "characterId": 22
      }
    ]
  },
  "costumeId": 1297,
  "gachaText": [
    "それに……あなたの喜んだ顔は、\n今でも覚えているから",
    "Besides... I still remember how happy you looked.",
    "再說……你當時開心的表情，\n我到現在也都還記得",
    "而且……我现在还记得\n你开心的表情",
    "게다가…… 당신의 기뻐하는 얼굴은\n지금도 기억하니까"
  ],
  "prefix": [
    "あなたは誰のために？",
    "For Whose Sake?",
    "你是為了誰而做？",
    "你是为了谁？",
    "당신은 누구를 위해서?"
  ],
  "releasedAt": [
    "1641880800000",
    "1667523600000",
    "1653289200000",
    "1641884400000",
    "1641880800000"
  ],
  "skillName": [
    "絵本の記憶",
    "Memory of a Children’s Book",
    "繪本的記憶",
    "图画书的记忆",
    "그림책의 기억"
  ],
  "skillId": 3,
  "source": null,
  "type": "permanent",
  "stat": {
    "1": {
      "performance": 2610,
      "technique": 3087,
      "visual": 3393
    },
    "2": {
      "performance": 2644,
      "technique": 3127,
      "visual": 3437
    },
    "3": {
      "performance": 2680,
      "technique": 3169,
      "visual": 3483
    },
    "4": {
      "performance": 2717,
      "technique": 3213,
      "visual": 3532
    },
    "5": {
      "performance": 2756,
      "technique": 3259,
      "visual": 3583
    },
    "6": {
      "performance": 2797,
      "technique": 3307,
      "visual": 3636
    },
    "7": {
      "performance": 2839,
      "technique": 3357,
      "visual": 3691
    },
    "8": {
      "performance": 2883,
      "technique": 3409,
      "visual": 3748
    },
    "9": {
      "performance": 2929,
      "technique": 3463,
      "visual": 3808
    },
    "10": {
      "performance": 2977,
      "technique": 3519,
      "visual": 3870
    },
    "11": {
      "performance": 3026,
      "technique": 3577,
      "visual": 3934
    },
    "12": {
      "performance": 3077,
      "technique": 3637,
      "visual": 4000
    },
    "13": {
      "performance": 3130,
      "technique": 3699,
      "visual": 4068
    },
    "14": {
      "performance": 3184,
      "technique": 3763,
      "visual": 4139
    },
    "15": {
      "performance": 3240,
      "technique": 3829,
      "visual": 4212
    },
    "16": {
      "performance": 3298,
      "technique": 3897,
      "visual": 4287
    },
    "17": {
      "performance": 3357,
      "technique": 3967,
      "visual": 4364
    },
    "18": {
      "performance": 3418,
      "technique": 4039,
      "visual": 4444
    },
    "19": {
      "performance": 3481,
      "technique": 4113,
      "visual": 4526
    },
    "20": {
      "performance": 3546,
      "technique": 4189,
      "visual": 4610
    },
    "21": {
      "performance": 3612,
      "technique": 4267,
      "visual": 4696
    },
    "22": {
      "performance": 3680,
      "technique": 4347,
      "visual": 4784
    },
    "23": {
      "performance": 3750,
      "technique": 4429,
      "visual": 4875
    },
    "24": {
      "performance": 3821,
      "technique": 4513,
      "visual": 4968
    },
    "25": {
      "performance": 3894,
      "technique": 4599,
      "visual": 5063
    },
    "26": {
      "performance": 3969,
      "technique": 4687,
      "visual": 5160
    },
    "27": {
      "performance": 4045,
      "technique": 4777,
      "visual": 5259
    },
    "28": {
      "performance": 4123,
      "technique": 4869,
      "visual": 5361
    },
    "29": {
      "performance": 4203,
      "technique": 4963,
      "visual": 5465
    },
    "30": {
      "performance": 4285,
      "technique": 5059,
      "visual": 5571
    },
    "31": {
      "performance": 4368,
      "technique": 5157,
      "visual": 5679
    },
    "32": {
      "performance": 4453,
      "technique": 5257,
      "visual": 5789
    },
    "33": {
      "performance": 4540,
      "technique": 5359,
      "visual": 5902
    },
    "34": {
      "performance": 4628,
      "technique": 5463,
      "visual": 6017
    },
    "35": {
      "performance": 4718,
      "technique": 5569,
      "visual": 6134
    },
    "36": {
      "performance": 4810,
      "technique": 5677,
      "visual": 6253
    },
    "37": {
      "performance": 4903,
      "technique": 5787,
      "visual": 6374
    },
    "38": {
      "performance": 4998,
      "technique": 5899,
      "visual": 6498
    },
    "39": {
      "performance": 5095,
      "technique": 6014,
      "visual": 6624
    },
    "40": {
      "performance": 5194,
      "technique": 6131,
      "visual": 6752
    },
    "41": {
      "performance": 5337,
      "technique": 6300,
      "visual": 6938
    },
    "42": {
      "performance": 5506,
      "technique": 6500,
      "visual": 7157
    },
    "43": {
      "performance": 5700,
      "technique": 6730,
      "visual": 7410
    },
    "44": {
      "performance": 5920,
      "technique": 6990,
      "visual": 7696
    },
    "45": {
      "performance": 6166,
      "technique": 7280,
      "visual": 8015
    },
    "46": {
      "performance": 6437,
      "technique": 7601,
      "visual": 8368
    },
    "47": {
      "performance": 6734,
      "technique": 7952,
      "visual": 8754
    },
    "48": {
      "performance": 7056,
      "technique": 8333,
      "visual": 9173
    },
    "49": {
      "performance": 7404,
      "technique": 8745,
      "visual": 9625
    },
    "50": {
      "performance": 7778,
      "technique": 9187,
      "visual": 10111
    },
    "episodes": [
      {
        "performance": 200,
        "technique": 200,
        "visual": 200
      },
      {
        "performance": 500,
        "technique": 500,
        "visual": 500
      }
    ],
    "training": {
      "levelLimit": 10,
      "performance": 300,
      "technique": 300,
      "visual": 300
    }
  }
}